openbaton_cli-6.0.0.data/scripts/openbaton
openbaton_cli-6.0.0.data/scripts/openbaton-v2
openbaton_cli-6.0.0.dist-info/METADATA
openbaton_cli-6.0.0.dist-info/RECORD
openbaton_cli-6.0.0.dist-info/WHEEL
openbaton_cli-6.0.0.dist-info/entry_points.txt
openbaton_cli-6.0.0.dist-info/top_level.txt
org/__init__.py
org/openbaton/__init__.py
org/openbaton/config.py
org/openbaton/utils.py
org/openbaton/cli/__init__.py
org/openbaton/cli/openbaton.py
org/openbaton/cli/agents/__init__.py
org/openbaton/cli/agents/agents.py
org/openbaton/cli/errors/__init__.py
org/openbaton/cli/errors/errors.py
org/openbaton/cli/utils/RestClient.py
org/openbaton/cli/utils/__init__.py
org/openbaton/sdk/__init__.py
org/openbaton/sdk/client.py
org/openbaton/v2/__init__.py
org/openbaton/v2/cmd.py
org/openbaton/v2/errors.py
org/openbaton/v2/events.py
org/openbaton/v2/keys.py
org/openbaton/v2/market.py
org/openbaton/v2/nsd.py
org/openbaton/v2/nsr.py
org/openbaton/v2/packages.py
org/openbaton/v2/projects.py
org/openbaton/v2/scripts.py
org/openbaton/v2/services.py
org/openbaton/v2/users.py
org/openbaton/v2/utils.py
org/openbaton/v2/vims.py
tests/__init__.py
tests/ob_cli_tests.py
