Metadata-Version: 2.1
Name: openbaton-cli
Version: 6.0.0
Summary: The Open Baton CLI
Home-page: http://openbaton.github.io/
Author: Open Baton
Author-email: dev@openbaton.org
License: Apache 2
Keywords: python vnfm nfvo open baton openbaton sdk cli rest
Platform: UNKNOWN
Classifier: Development Status :: 4 - Beta
Classifier: Intended Audience :: Developers
Classifier: Topic :: Software Development :: Build Tools
Classifier: Topic :: Utilities
Classifier: License :: OSI Approved :: Apache Software License
Requires-Dist: requests
Requires-Dist: tabulate
Requires-Dist: argcomplete
Requires-Dist: configparser
Requires-Dist: asyncio
Requires-Dist: cliff
